datashare_python-0.1.3.dist-info/METADATA
datashare_python-0.1.3.dist-info/WHEEL
datashare_python-0.1.3.dist-info/entry_points.txt
datashare_python/__init__.py
datashare_python/__main__.py
datashare_python/app.py
datashare_python/cli/__init__.py
datashare_python/cli/tasks.py
datashare_python/cli/utils.py
datashare_python/config.py
datashare_python/constants.py
datashare_python/objects.py
datashare_python/task_client.py
datashare_python/tasks/__init__.py
datashare_python/tasks/classify_docs.py
datashare_python/tasks/dependencies.py
datashare_python/tasks/translate_docs.py
datashare_python/utils.py
datashare_python-0.1.3.dist-info/RECORD
