Metadata-Version: 2.1
Name: datashare-python
Version: 0.1.3
Summary: Implement Datashare task in Python
Author-Email: =?utf-8?q?Cl=C3=A9ment_Doumouro?= <cdoumouro@icij.org>, =?utf-8?q?Cl=C3=A9ment_Doumouro?= <clement.doumouro@gmail.com>
Project-URL: Homepage, https://icij.github.io/datashare-python/
Project-URL: Documentation, https://icij.github.io/datashare-python/
Project-URL: Repository, https://github.com/ICIJ/datashare-python
Project-URL: Issues, https://github.com/ICIJ/datashare-python/issues
Requires-Python: ~=3.11
Requires-Dist: aiostream~=0.6.4
Requires-Dist: aiohttp~=3.11.9
Requires-Dist: icij-common[elasticsearch]~=0.5.5
Requires-Dist: icij-worker[amqp]~=0.13
Requires-Dist: torch==2.6.0.dev20241101; sys_platform != "darwin"
Requires-Dist: torch!=2.6.0.dev20241101+cpu,<=2.6.0.dev20241101; sys_platform == "darwin"
Requires-Dist: transformers~=4.46.3
Requires-Dist: pycountry>=24.6.1
Requires-Dist: sentencepiece>=0.2.0
Requires-Dist: typer>=0.13.1
Requires-Dist: alive-progress>=3.2.0
